genhpf/__init__.py
genhpf/trainer.py
genhpf/configs/__init__.py
genhpf/configs/config.yaml
genhpf/configs/configs.py
genhpf/configs/constants.py
genhpf/configs/initialize.py
genhpf/configs/utils.py
genhpf/criterions/__init__.py
genhpf/criterions/binary_cross_entropy.py
genhpf/criterions/binary_cross_entropy_with_logits.py
genhpf/criterions/criterion.py
genhpf/criterions/cross_entropy.py
genhpf/criterions/multi_task_criterion.py
genhpf/criterions/simclr_criterion.py
genhpf/criterions/wav2vec2_criterion.py
genhpf/datasets/__init__.py
genhpf/datasets/dataset.py
genhpf/datasets/genhpf_dataset.py
genhpf/datasets/meds_dataset.py
genhpf/loggings/__init__.py
genhpf/loggings/meters.py
genhpf/loggings/metrics.py
genhpf/loggings/progress_bar.py
genhpf/models/__init__.py
genhpf/models/genhpf.py
genhpf/models/genhpf_mlm.py
genhpf/models/genhpf_predictor.py
genhpf/models/genhpf_simclr.py
genhpf/models/genhpf_wav2vec2.py
genhpf/modules/__init__.py
genhpf/modules/gather_layer.py
genhpf/modules/grad_multiply.py
genhpf/modules/gumbel_vector_quantizer.py
genhpf/modules/identity_layer.py
genhpf/modules/layer_norm.py
genhpf/modules/positional_encoding.py
genhpf/scripts/__init__.py
genhpf/scripts/test.py
genhpf/scripts/train.py
genhpf/scripts/preprocess/__init__.py
genhpf/scripts/preprocess/manifest.py
genhpf/scripts/preprocess/preprocess_meds.py
genhpf/scripts/preprocess/genhpf/README.md
genhpf/scripts/preprocess/genhpf/__init__.py
genhpf/scripts/preprocess/genhpf/main.py
genhpf/scripts/preprocess/genhpf/manifest.py
genhpf/scripts/preprocess/genhpf/sample_dataset.py
genhpf/scripts/preprocess/genhpf/ehrs/__init__.py
genhpf/scripts/preprocess/genhpf/ehrs/ehr.py
genhpf/scripts/preprocess/genhpf/ehrs/eicu.py
genhpf/scripts/preprocess/genhpf/ehrs/mimiciii.py
genhpf/scripts/preprocess/genhpf/ehrs/mimiciv.py
genhpf/scripts/preprocess/genhpf/utils/__init__.py
genhpf/scripts/preprocess/genhpf/utils/utils.py
genhpf/utils/checkpoint_utils.py
genhpf/utils/data_utils.py
genhpf-1.0.10.dist-info/LICENSE
genhpf-1.0.10.dist-info/METADATA
genhpf-1.0.10.dist-info/WHEEL
genhpf-1.0.10.dist-info/entry_points.txt
genhpf-1.0.10.dist-info/top_level.txt
genhpf-1.0.10.dist-info/RECORD
