Metadata-Version: 2.2
Name: genhpf
Version: 1.0.10
Summary: GenHPF: General Healthcare Predictive Framework with Multi-task Multi-source Learning
Author-email: Jungwoo Oh <ojw0123@kaist.ac.kr>, Kyunghoon Hur <pacesun@kaist.ac.kr>
License: MIT license
Classifier: Intended Audience :: Science/Research
Classifier: Programming Language :: Python :: 3
Classifier: Topic :: Scientific/Engineering :: Artificial Intelligence
Requires-Python: >=3.10.0
License-File: LICENSE
Requires-Dist: hydra-core==1.3.2
Requires-Dist: omegaconf==2.3.0
Requires-Dist: torch==2.6.0
Requires-Dist: transformers==4.49.0
Requires-Dist: h5pickle==0.4.2
Requires-Dist: scikit-learn==1.6.1
Requires-Dist: pandas==2.2.3
Requires-Dist: polars==1.17.1
Requires-Dist: pyarrow==17.0.0
Provides-Extra: dev
Requires-Dist: pre-commit; extra == "dev"
Requires-Dist: black; extra == "dev"
